networkx/__init__.py
networkx/conftest.py
networkx/convert.py
networkx/convert_matrix.py
networkx/exception.py
networkx/lazy_imports.py
networkx/relabel.py
networkx/algorithms/__init__.py
networkx/algorithms/asteroidal.py
networkx/algorithms/boundary.py
networkx/algorithms/bridges.py
networkx/algorithms/broadcasting.py
networkx/algorithms/chains.py
networkx/algorithms/chordal.py
networkx/algorithms/clique.py
networkx/algorithms/cluster.py
networkx/algorithms/communicability_alg.py
networkx/algorithms/core.py
networkx/algorithms/covering.py
networkx/algorithms/cuts.py
networkx/algorithms/cycles.py
networkx/algorithms/d_separation.py
networkx/algorithms/dag.py
networkx/algorithms/distance_measures.py
networkx/algorithms/distance_regular.py
networkx/algorithms/dominance.py
networkx/algorithms/dominating.py
networkx/algorithms/efficiency_measures.py
networkx/algorithms/euler.py
networkx/algorithms/graph_hashing.py
networkx/algorithms/graphical.py
networkx/algorithms/hierarchy.py
networkx/algorithms/hybrid.py
networkx/algorithms/isolate.py
networkx/algorithms/link_prediction.py
networkx/algorithms/lowest_common_ancestors.py
networkx/algorithms/matching.py
networkx/algorithms/mis.py
networkx/algorithms/moral.py
networkx/algorithms/node_classification.py
networkx/algorithms/non_randomness.py
networkx/algorithms/planar_drawing.py
networkx/algorithms/planarity.py
networkx/algorithms/polynomials.py
networkx/algorithms/reciprocity.py
networkx/algorithms/regular.py
networkx/algorithms/richclub.py
networkx/algorithms/similarity.py
networkx/algorithms/simple_paths.py
networkx/algorithms/smallworld.py
networkx/algorithms/smetric.py
networkx/algorithms/sparsifiers.py
networkx/algorithms/structuralholes.py
networkx/algorithms/summarization.py
networkx/algorithms/swap.py
networkx/algorithms/threshold.py
networkx/algorithms/time_dependent.py
networkx/algorithms/tournament.py
networkx/algorithms/triads.py
networkx/algorithms/vitality.py
networkx/algorithms/voronoi.py
networkx-3.4.dist-info/LICENSE.txt
networkx-3.4.dist-info/METADATA
networkx-3.4.dist-info/WHEEL
networkx-3.4.dist-info/entry_points.txt
networkx-3.4.dist-info/top_level.txt
networkx-3.4.dist-info/RECORD
