Metadata-Version: 2.1
Name: networkx
Version: 3.4
Summary: Python package for creating and manipulating graphs and networks
Author-email: Aric Hagberg <hagberg@lanl.gov>
Maintainer-email: NetworkX Developers <networkx-discuss@googlegroups.com>
Project-URL: Homepage, https://networkx.org/
Project-URL: Bug Tracker, https://github.com/networkx/networkx/issues
Project-URL: Documentation, https://networkx.org/documentation/stable/
Project-URL: Source Code, https://github.com/networkx/networkx
Keywords: Networks,Graph Theory,Mathematics,network,graph,discrete mathematics,math
Platform: Linux
Platform: Mac OSX
Platform: Windows
Platform: Unix
Classifier: Development Status :: 5 - Production/Stable
Classifier: Intended Audience :: Developers
Classifier: Intended Audience :: Science/Research
Classifier: License :: OSI Approved :: BSD License
Classifier: Operating System :: OS Independent
Classifier: Programming Language :: Python :: 3
Classifier: Programming Language :: Python :: 3.10
Classifier: Programming Language :: Python :: 3.11
Classifier: Programming Language :: Python :: 3.12
Classifier: Programming Language :: Python :: 3.13
Classifier: Programming Language :: Python :: 3 :: Only
Classifier: Topic :: Software Development :: Libraries :: Python Modules
Classifier: Topic :: Scientific/Engineering :: Bio-Informatics
Classifier: Topic :: Scientific/Engineering :: Information Analysis
Classifier: Topic :: Scientific/Engineering :: Mathematics
Classifier: Topic :: Scientific/Engineering :: Physics
Requires-Python: >=3.10
License-File: LICENSE.txt
Provides-Extra: default
Requires-Dist: numpy>=1.24; extra == "default"
Requires-Dist: scipy!=1.11.0,!=1.11.1,>=1.10; extra == "default"
Requires-Dist: matplotlib>=3.7; extra == "default"
Requires-Dist: pandas>=2.0; extra == "default"
Provides-Extra: developer
Requires-Dist: changelist==0.5; extra == "developer"
Requires-Dist: pre-commit>=3.2; extra == "developer"
Requires-Dist: mypy>=1.1; extra == "developer"
Requires-Dist: rtoml; extra == "developer"
Provides-Extra: doc
Requires-Dist: sphinx>=7.3; extra == "doc"
Requires-Dist: pydata-sphinx-theme>=0.15; extra == "doc"
Requires-Dist: sphinx-gallery>=0.16; extra == "doc"
Requires-Dist: numpydoc>=1.8.0; extra == "doc"
Requires-Dist: pillow>=9.4; extra == "doc"
Requires-Dist: texext>=0.6.7; extra == "doc"
Requires-Dist: myst-nb>=1.1; extra == "doc"
Requires-Dist: intersphinx_registry; extra == "doc"
Provides-Extra: example
Requires-Dist: osmnx>=1.9; extra == "example"
Requires-Dist: momepy>=0.7.2; extra == "example"
Requires-Dist: contextily>=1.6; extra == "example"
Requires-Dist: seaborn>=0.13; extra == "example"
Requires-Dist: cairocffi>=1.7; extra == "example"
Requires-Dist: igraph>=0.11; extra == "example"
Requires-Dist: scikit-learn>=1.5; extra == "example"
Provides-Extra: extra
Requires-Dist: lxml>=4.6; extra == "extra"
Requires-Dist: pygraphviz>=1.14; extra == "extra"
Requires-Dist: pydot>=3.0.1; extra == "extra"
Requires-Dist: sympy>=1.10; extra == "extra"
Provides-Extra: test
Requires-Dist: pytest>=7.2; extra == "test"
Requires-Dist: pytest-cov>=4.0; extra == "test"
